delta_utils/__init__.py
delta_utils/check_choose_move_output.py
delta_utils/check_saved_file.py
delta_utils/check_submission.py
delta_utils/hash_game_mechanics.py
delta_utils/utils.py
delta_utils-0.1.1.dist-info/METADATA
delta_utils-0.1.1.dist-info/WHEEL
delta_utils-0.1.1.dist-info/entry_points.txt
delta_utils-0.1.1.dist-info/licenses/LICENSE
delta_utils-0.1.1.dist-info/RECORD
