Metadata-Version: 2.1
Name: delta-utils
Version: 0.1.1
Summary: Utility tools for Delta Academy tournaments
Project-URL: Homepage, https://github.com/Delta-Academy/delta-utils/
Author-email: neuromantic99 <james@learney.me>
License-File: LICENSE
Classifier: License :: OSI Approved :: MIT License
Classifier: Operating System :: OS Independent
Classifier: Programming Language :: Python :: 3
Requires-Python: >=3.8
Requires-Dist: dirhash
